{"name":"Login exitoso con credenciales válidas","id":"autenticacion-en-orangehrm;login-exitoso-con-credenciales-válidas","scenarioId":"login:Login exitoso con credenciales válidas","methodName":"Login exitoso con credenciales válidas","testSteps":[{"number":1,"description":"Given que estoy en la pagina de login de OrangeHRM","duration":4288,"startTime":"2025-07-05T06:17:13.679638600-05:00[America/Bogota]","result":"SUCCESS","precondition":false,"level":0,"children":[{"number":2,"description":"user opens the browser at https://opensource-demo.orangehrmlive.com/web/index.php/auth/login","duration":3581,"startTime":"2025-07-05T06:17:14.365558400-05:00[America/Bogota]","result":"SUCCESS","precondition":false,"level":1}]},{"number":3,"description":"When ingreso el usuario \"Admin\" y la contrasena \"admin123\"","duration":1634,"startTime":"2025-07-05T06:17:17.975111100-05:00[America/Bogota]","result":"SUCCESS","precondition":false,"level":0,"children":[{"number":4,"description":"User login","duration":1598,"startTime":"2025-07-05T06:17:17.995741-05:00[America/Bogota]","result":"SUCCESS","precondition":false,"level":1,"children":[{"number":5,"description":"user enters \u0027Admin\u0027 into username field","duration":436,"startTime":"2025-07-05T06:17:18.826445-05:00[America/Bogota]","result":"SUCCESS","precondition":false,"level":2},{"number":6,"description":"user enters \u0027admin123\u0027 into password field","duration":316,"startTime":"2025-07-05T06:17:19.264135600-05:00[America/Bogota]","result":"SUCCESS","precondition":false,"level":2}]}]},{"number":7,"description":"And hago clic en el boton \"Login\"","duration":716,"startTime":"2025-07-05T06:17:19.611623800-05:00[America/Bogota]","result":"SUCCESS","precondition":false,"level":0,"children":[{"number":8,"description":"User click login button","duration":680,"startTime":"2025-07-05T06:17:19.630571600-05:00[America/Bogota]","result":"SUCCESS","precondition":false,"level":1,"children":[{"number":9,"description":"user clicks on login button","duration":411,"startTime":"2025-07-05T06:17:19.871875100-05:00[America/Bogota]","result":"SUCCESS","precondition":false,"level":2}]}]},{"number":10,"description":"Then debo estar autenticado y ver el dashboard","duration":2209,"startTime":"2025-07-05T06:17:20.328501900-05:00[America/Bogota]","result":"SUCCESS","precondition":false,"level":0,"children":[{"number":11,"description":"Then Dashboard should be visible should be (true)","duration":1955,"startTime":"2025-07-05T06:17:20.539405700-05:00[America/Bogota]","result":"SUCCESS","precondition":false,"level":1}]},{"number":12,"description":"And debo ver el nombre de usuario en la esquina superior derecha","duration":549,"startTime":"2025-07-05T06:17:22.544075400-05:00[America/Bogota]","result":"SUCCESS","precondition":false,"level":0,"children":[{"number":13,"description":"Then User profile should be displayed should be (true)","duration":517,"startTime":"2025-07-05T06:17:22.557329200-05:00[America/Bogota]","result":"SUCCESS","precondition":false,"level":1}]}],"userStory":{"id":"login","storyName":"Autenticacion en OrangeHRM","displayName":"Autenticacion en OrangeHRM","path":"login","pathElements":[{"name":"login","description":""}],"narrative":"  Como usuario del sistema OrangeHRM\n  Quiero poder iniciar sesion con mis credenciales\n  Para acceder al dashboard del sistema","type":"feature"},"title":"Login exitoso con credenciales válidas","description":"","tags":[{"name":"Chrome","type":"context","displayName":"Chrome"},{"name":"Windows","type":"context","displayName":"Windows"},{"name":"Chrome, Windows","type":"context","displayName":"Chrome, Windows"}],"startTime":"2025-07-05T06:17:13.409105800-05:00[America/Bogota]","duration":4533,"projectKey":"","sessionId":"d0ca4ff54cc0ab0346c214d627e29ec4","driver":"chrome:user","isManualTestingUpToDate":false,"context":"chrome,windows","manual":false,"testSource":"Cucumber","actors":[{"name":"user","can":["browse the web"]}],"order":0,"result":"SUCCESS"}